pydefillama/__init__.py
pydefillama/src/__init__.py
pydefillama/src/fetcher.py
pydefillama/src/utils.py
pydefillama/tests/__init__.py
pydefillama/tests/fetcher_tests.py
pydefillama-1.0.10.dist-info/LICENSE
pydefillama-1.0.10.dist-info/METADATA
pydefillama-1.0.10.dist-info/WHEEL
pydefillama-1.0.10.dist-info/top_level.txt
pydefillama-1.0.10.dist-info/RECORD
