Metadata-Version: 2.1
Name: pydefillama
Version: 1.0.10
Summary: Python Wrapper for DefiLlama endpoints
Home-page: https://github.com/Artemis-xyz/DefiLlama-Python-Client
Author: Artemis.xyz
Author-email: team@artemis.xyz
License: MIT
License-File: LICENSE
Requires-Dist: pandas
Requires-Dist: numpy
Requires-Dist: wheel
Requires-Dist: requests
